setup.py
climb/__init__.py
climb/args.py
climb/commands.py
climb/completer.py
climb/config.py
climb/core.py
climb/exceptions.py
climb/paths.py
climb.egg-info/PKG-INFO
climb.egg-info/SOURCES.txt
climb.egg-info/dependency_links.txt
climb.egg-info/top_level.txt