Metadata-Version: 1.1
Name: climb
Version: 0.3.2
Summary: Library for interactive command line applications.
Home-page: https://github.com/m110/climb
Author: Milosz Smolka
Author-email: m110@m110.pl
License: UNKNOWN
Platform: UNKNOWN
Classifier: Development Status :: 3 - Alpha
Classifier: Environment :: Console
Classifier: Intended Audience :: Developers
Classifier: Intended Audience :: System Administrators
Classifier: License :: OSI Approved :: MIT License
Classifier: Operating System :: POSIX
Classifier: Programming Language :: Python :: 3.4
Classifier: Topic :: System :: Systems Administration
